{
"result":{
"players":[
{
"account_id":161853388,
"player_slot":0,
"hero_id":15,
"item_0":147,
"item_1":212,
"item_2":210,
"item_3":50,
"item_4":116,
"item_5":32,
"kills":14,
"deaths":10,
"assists":13,
"leaver_status":0,
"last_hits":206,
"denies":15,
"gold_per_min":563,
"xp_per_min":537,
"level":21,
"hero_damage":28116,
"tower_damage":2130,
"hero_healing":0,
"gold":2121,
"gold_spent":19235,
"scaled_hero_damage":18359,
"scaled_tower_damage":1654,
"scaled_hero_healing":0,
"ability_upgrades":[
{
"ability":5083,
"time":446,
"level":1
},
{
"ability":5084,
"time":527,
"level":2
},
{
"ability":5083,
"time":576,
"level":3
},
{
"ability":5082,
"time":660,
"level":4
},
{
"ability":5083,
"time":700,
"level":5
},
{
"ability":5085,
"time":776,
"level":6
},
{
"ability":5082,
"time":859,
"level":7
},
{
"ability":5082,
"time":934,
"level":8
},
{
"ability":5082,
"time":1046,
"level":9
},
{
"ability":5084,
"time":1149,
"level":10
},
{
"ability":5085,
"time":1171,
"level":11
},
{
"ability":5084,
"time":1520,
"level":12
},
{
"ability":5083,
"time":1560,
"level":13
},
{
"ability":5084,
"time":1701,
"level":14
},
{
"ability":5002,
"time":1973,
"level":15
},
{
"ability":5085,
"time":2016,
"level":16
},
{
"ability":5002,
"time":2348,
"level":17
},
{
"ability":5002,
"time":2426,
"level":18
},
{
"ability":5002,
"time":2466,
"level":19
},
{
"ability":5002,
"time":2660,
"level":20
},
{
"ability":5002,
"time":2982,
"level":21
}
]

},
{
"account_id":4294967295,
"player_slot":1,
"hero_id":8,
"item_0":208,
"item_1":139,
"item_2":147,
"item_3":48,
"item_4":145,
"item_5":196,
"kills":10,
"deaths":3,
"assists":13,
"leaver_status":0,
"last_hits":341,
"denies":10,
"gold_per_min":706,
"xp_per_min":766,
"level":25,
"hero_damage":42082,
"tower_damage":9563,
"hero_healing":0,
"gold":350,
"gold_spent":31985,
"scaled_hero_damage":23077,
"scaled_tower_damage":6874,
"scaled_hero_healing":0,
"ability_upgrades":[
{
"ability":5028,
"time":448,
"level":1
},
{
"ability":5027,
"time":536,
"level":2
},
{
"ability":5028,
"time":562,
"level":3
},
{
"ability":5027,
"time":610,
"level":4
},
{
"ability":5028,
"time":737,
"level":5
},
{
"ability":5030,
"time":835,
"level":6
},
{
"ability":5027,
"time":920,
"level":7
},
{
"ability":5029,
"time":985,
"level":8
},
{
"ability":5028,
"time":1146,
"level":9
},
{
"ability":5027,
"time":1256,
"level":10
},
{
"ability":5030,
"time":1330,
"level":11
},
{
"ability":5029,
"time":1536,
"level":12
},
{
"ability":5029,
"time":1584,
"level":13
},
{
"ability":5002,
"time":1684,
"level":14
},
{
"ability":5002,
"time":1753,
"level":15
},
{
"ability":5030,
"time":1858,
"level":16
},
{
"ability":5029,
"time":2023,
"level":17
},
{
"ability":5002,
"time":2122,
"level":18
},
{
"ability":5002,
"time":2291,
"level":19
},
{
"ability":5002,
"time":2432,
"level":20
},
{
"ability":5002,
"time":2565,
"level":21
},
{
"ability":5002,
"time":2626,
"level":22
},
{
"ability":5002,
"time":2762,
"level":23
},
{
"ability":5002,
"time":2942,
"level":24
}
]

},
{
"account_id":4294967295,
"player_slot":2,
"hero_id":98,
"item_0":48,
"item_1":119,
"item_2":242,
"item_3":100,
"item_4":121,
"item_5":36,
"kills":2,
"deaths":5,
"assists":18,
"leaver_status":0,
"last_hits":209,
"denies":2,
"gold_per_min":489,
"xp_per_min":646,
"level":23,
"hero_damage":26051,
"tower_damage":782,
"hero_healing":2805,
"gold":105,
"gold_spent":20610,
"scaled_hero_damage":16092,
"scaled_tower_damage":525,
"scaled_hero_healing":944,
"ability_upgrades":[
{
"ability":5526,
"time":442,
"level":1
},
{
"ability":5525,
"time":532,
"level":2
},
{
"ability":5526,
"time":613,
"level":3
},
{
"ability":5525,
"time":678,
"level":4
},
{
"ability":5526,
"time":738,
"level":5
},
{
"ability":5527,
"time":846,
"level":6
},
{
"ability":5525,
"time":903,
"level":7
},
{
"ability":5525,
"time":1032,
"level":8
},
{
"ability":5524,
"time":1108,
"level":9
},
{
"ability":5524,
"time":1199,
"level":10
},
{
"ability":5527,
"time":1277,
"level":11
},
{
"ability":5526,
"time":1502,
"level":12
},
{
"ability":5524,
"time":1534,
"level":13
},
{
"ability":5524,
"time":1671,
"level":14
},
{
"ability":5002,
"time":1909,
"level":15
},
{
"ability":5527,
"time":2086,
"level":16
},
{
"ability":5002,
"time":2450,
"level":17
},
{
"ability":5002,
"time":2626,
"level":18
},
{
"ability":5002,
"time":2815,
"level":19
},
{
"ability":5002,
"time":2907,
"level":20
},
{
"ability":5002,
"time":2961,
"level":21
},
{
"ability":5002,
"time":3024,
"level":22
},
{
"ability":5002,
"time":3036,
"level":23
}
]

},
{
"account_id":4294967295,
"player_slot":3,
"hero_id":4,
"item_0":139,
"item_1":154,
"item_2":81,
"item_3":63,
"item_4":127,
"item_5":46,
"kills":9,
"deaths":7,
"assists":12,
"leaver_status":0,
"last_hits":189,
"denies":1,
"gold_per_min":477,
"xp_per_min":500,
"level":20,
"hero_damage":24109,
"tower_damage":3227,
"hero_healing":7956,
"gold":2545,
"gold_spent":17430,
"scaled_hero_damage":14697,
"scaled_tower_damage":2497,
"scaled_hero_healing":4582,
"ability_upgrades":[
{
"ability":5016,
"time":457,
"level":1
},
{
"ability":5015,
"time":507,
"level":2
},
{
"ability":5015,
"time":567,
"level":3
},
{
"ability":5017,
"time":661,
"level":4
},
{
"ability":5015,
"time":726,
"level":5
},
{
"ability":5018,
"time":797,
"level":6
},
{
"ability":5016,
"time":868,
"level":7
},
{
"ability":5016,
"time":960,
"level":8
},
{
"ability":5016,
"time":1159,
"level":9
},
{
"ability":5017,
"time":1219,
"level":10
},
{
"ability":5018,
"time":1425,
"level":11
},
{
"ability":5015,
"time":1905,
"level":12
},
{
"ability":5017,
"time":2029,
"level":13
},
{
"ability":5017,
"time":2259,
"level":14
},
{
"ability":5002,
"time":2426,
"level":15
},
{
"ability":5018,
"time":2444,
"level":16
},
{
"ability":5002,
"time":2623,
"level":17
},
{
"ability":5002,
"time":2631,
"level":18
},
{
"ability":5002,
"time":2828,
"level":19
},
{
"ability":5002,
"time":2917,
"level":20
}
]

},
{
"account_id":4294967295,
"player_slot":4,
"hero_id":14,
"item_0":1,
"item_1":152,
"item_2":36,
"item_3":37,
"item_4":232,
"item_5":180,
"kills":5,
"deaths":12,
"assists":15,
"leaver_status":0,
"last_hits":63,
"denies":1,
"gold_per_min":348,
"xp_per_min":405,
"level":18,
"hero_damage":17602,
"tower_damage":583,
"hero_healing":0,
"gold":707,
"gold_spent":13645,
"scaled_hero_damage":11256,
"scaled_tower_damage":401,
"scaled_hero_healing":0,
"ability_upgrades":[
{
"ability":5076,
"time":476,
"level":1
},
{
"ability":5075,
"time":524,
"level":2
},
{
"ability":5075,
"time":624,
"level":3
},
{
"ability":5076,
"time":868,
"level":4
},
{
"ability":5075,
"time":1074,
"level":5
},
{
"ability":5077,
"time":1102,
"level":6
},
{
"ability":5075,
"time":1166,
"level":7
},
{
"ability":5076,
"time":1334,
"level":8
},
{
"ability":5076,
"time":1500,
"level":9
},
{
"ability":5074,
"time":1573,
"level":10
},
{
"ability":5077,
"time":1698,
"level":11
},
{
"ability":5074,
"time":2033,
"level":12
},
{
"ability":5074,
"time":2033,
"level":13
},
{
"ability":5074,
"time":2482,
"level":14
},
{
"ability":5002,
"time":2700,
"level":15
},
{
"ability":5077,
"time":2827,
"level":16
},
{
"ability":5002,
"time":2905,
"level":17
},
{
"ability":5002,
"time":2984,
"level":18
}
]

},
{
"account_id":309188378,
"player_slot":128,
"hero_id":6,
"item_0":63,
"item_1":263,
"item_2":36,
"item_3":212,
"item_4":166,
"item_5":108,
"kills":2,
"deaths":9,
"assists":18,
"leaver_status":0,
"last_hits":241,
"denies":21,
"gold_per_min":428,
"xp_per_min":484,
"level":20,
"hero_damage":12211,
"tower_damage":966,
"hero_healing":0,
"gold":1024,
"gold_spent":15220,
"scaled_hero_damage":6235,
"scaled_tower_damage":594,
"scaled_hero_healing":0,
"ability_upgrades":[
{
"ability":5021,
"time":453,
"level":1
},
{
"ability":5632,
"time":530,
"level":2
},
{
"ability":5021,
"time":570,
"level":3
},
{
"ability":5019,
"time":637,
"level":4
},
{
"ability":5632,
"time":736,
"level":5
},
{
"ability":5022,
"time":892,
"level":6
},
{
"ability":5019,
"time":973,
"level":7
},
{
"ability":5021,
"time":1138,
"level":8
},
{
"ability":5019,
"time":1307,
"level":9
},
{
"ability":5632,
"time":1416,
"level":10
},
{
"ability":5022,
"time":1458,
"level":11
},
{
"ability":5021,
"time":1806,
"level":12
},
{
"ability":5632,
"time":1874,
"level":13
},
{
"ability":5019,
"time":2057,
"level":14
},
{
"ability":5002,
"time":2175,
"level":15
},
{
"ability":5022,
"time":2218,
"level":16
},
{
"ability":5002,
"time":2400,
"level":17
},
{
"ability":5002,
"time":2590,
"level":18
},
{
"ability":5002,
"time":2786,
"level":19
},
{
"ability":5002,
"time":3018,
"level":20
}
]

},
{
"account_id":30353416,
"player_slot":129,
"hero_id":37,
"item_0":88,
"item_1":180,
"item_2":108,
"item_3":69,
"item_4":46,
"item_5":36,
"kills":9,
"deaths":12,
"assists":20,
"leaver_status":0,
"last_hits":104,
"denies":6,
"gold_per_min":374,
"xp_per_min":347,
"level":16,
"hero_damage":40199,
"tower_damage":517,
"hero_healing":1755,
"gold":1981,
"gold_spent":11225,
"scaled_hero_damage":23307,
"scaled_tower_damage":281,
"scaled_hero_healing":1364,
"ability_upgrades":[
{
"ability":5162,
"time":481,
"level":1
},
{
"ability":5163,
"time":525,
"level":2
},
{
"ability":5162,
"time":673,
"level":3
},
{
"ability":5163,
"time":741,
"level":4
},
{
"ability":5162,
"time":838,
"level":5
},
{
"ability":5165,
"time":950,
"level":6
},
{
"ability":5162,
"time":1036,
"level":7
},
{
"ability":5163,
"time":1153,
"level":8
},
{
"ability":5163,
"time":1249,
"level":9
},
{
"ability":5165,
"time":1457,
"level":10
},
{
"ability":5164,
"time":1460,
"level":11
},
{
"ability":5164,
"time":1792,
"level":12
},
{
"ability":5164,
"time":1838,
"level":13
},
{
"ability":5164,
"time":2202,
"level":14
},
{
"ability":5002,
"time":2523,
"level":15
},
{
"ability":5165,
"time":2730,
"level":16
}
]

},
{
"account_id":321559036,
"player_slot":130,
"hero_id":70,
"item_0":1,
"item_1":50,
"item_2":208,
"item_3":0,
"item_4":172,
"item_5":0,
"kills":7,
"deaths":9,
"assists":12,
"leaver_status":0,
"last_hits":91,
"denies":2,
"gold_per_min":393,
"xp_per_min":523,
"level":20,
"hero_damage":23170,
"tower_damage":388,
"hero_healing":0,
"gold":1814,
"gold_spent":14260,
"scaled_hero_damage":13039,
"scaled_tower_damage":342,
"scaled_hero_healing":0,
"ability_upgrades":[
{
"ability":5359,
"time":446,
"level":1
},
{
"ability":5358,
"time":558,
"level":2
},
{
"ability":5357,
"time":596,
"level":3
},
{
"ability":5359,
"time":664,
"level":4
},
{
"ability":5359,
"time":717,
"level":5
},
{
"ability":5360,
"time":854,
"level":6
},
{
"ability":5359,
"time":1030,
"level":7
},
{
"ability":5358,
"time":1208,
"level":8
},
{
"ability":5358,
"time":1367,
"level":9
},
{
"ability":5358,
"time":1435,
"level":10
},
{
"ability":5360,
"time":1648,
"level":11
},
{
"ability":5357,
"time":1825,
"level":12
},
{
"ability":5357,
"time":1877,
"level":13
},
{
"ability":5357,
"time":1994,
"level":14
},
{
"ability":5002,
"time":2037,
"level":15
},
{
"ability":5360,
"time":2119,
"level":16
},
{
"ability":5002,
"time":2178,
"level":17
},
{
"ability":5002,
"time":2368,
"level":18
},
{
"ability":5002,
"time":2542,
"level":19
},
{
"ability":5002,
"time":3001,
"level":20
}
]

},
{
"account_id":33943646,
"player_slot":131,
"hero_id":79,
"item_0":231,
"item_1":46,
"item_2":36,
"item_3":102,
"item_4":100,
"item_5":218,
"kills":10,
"deaths":5,
"assists":16,
"leaver_status":0,
"last_hits":57,
"denies":3,
"gold_per_min":354,
"xp_per_min":478,
"level":19,
"hero_damage":28996,
"tower_damage":191,
"hero_healing":3782,
"gold":513,
"gold_spent":15450,
"scaled_hero_damage":14454,
"scaled_tower_damage":151,
"scaled_hero_healing":1722,
"ability_upgrades":[
{
"ability":5421,
"time":362,
"level":1
},
{
"ability":5423,
"time":598,
"level":2
},
{
"ability":5423,
"time":673,
"level":3
},
{
"ability":5422,
"time":769,
"level":4
},
{
"ability":5423,
"time":922,
"level":5
},
{
"ability":5425,
"time":1205,
"level":6
},
{
"ability":5423,
"time":1272,
"level":7
},
{
"ability":5422,
"time":1314,
"level":8
},
{
"ability":5422,
"time":1456,
"level":9
},
{
"ability":5422,
"time":1459,
"level":10
},
{
"ability":5425,
"time":1506,
"level":11
},
{
"ability":5421,
"time":1809,
"level":12
},
{
"ability":5421,
"time":1872,
"level":13
},
{
"ability":5421,
"time":1983,
"level":14
},
{
"ability":5002,
"time":2028,
"level":15
},
{
"ability":5425,
"time":2167,
"level":16
},
{
"ability":5002,
"time":2343,
"level":17
},
{
"ability":5002,
"time":2482,
"level":18
},
{
"ability":5002,
"time":2703,
"level":19
}
]

},
{
"account_id":133932996,
"player_slot":132,
"hero_id":102,
"item_0":50,
"item_1":108,
"item_2":154,
"item_3":81,
"item_4":181,
"item_5":46,
"kills":7,
"deaths":9,
"assists":12,
"leaver_status":0,
"last_hits":105,
"denies":7,
"gold_per_min":365,
"xp_per_min":426,
"level":18,
"hero_damage":19152,
"tower_damage":63,
"hero_healing":7544,
"gold":428,
"gold_spent":13990,
"scaled_hero_damage":10249,
"scaled_tower_damage":59,
"scaled_hero_healing":3838,
"ability_upgrades":[
{
"ability":5586,
"time":417,
"level":1
},
{
"ability":5587,
"time":524,
"level":2
},
{
"ability":5586,
"time":639,
"level":3
},
{
"ability":5585,
"time":757,
"level":4
},
{
"ability":5586,
"time":789,
"level":5
},
{
"ability":5588,
"time":939,
"level":6
},
{
"ability":5586,
"time":992,
"level":7
},
{
"ability":5585,
"time":1075,
"level":8
},
{
"ability":5585,
"time":1229,
"level":9
},
{
"ability":5588,
"time":1317,
"level":10
},
{
"ability":5585,
"time":1318,
"level":11
},
{
"ability":5587,
"time":1764,
"level":12
},
{
"ability":5587,
"time":1927,
"level":13
},
{
"ability":5587,
"time":2177,
"level":14
},
{
"ability":5002,
"time":2427,
"level":15
},
{
"ability":5588,
"time":2703,
"level":16
},
{
"ability":5002,
"time":2815,
"level":17
},
{
"ability":5002,
"time":2818,
"level":18
}
]

}
]
,
"radiant_win":true,
"duration":2595,
"pre_game_duration":90,
"start_time":1479781353,
"match_id":2794893373,
"match_seq_num":2438814350,
"tower_status_radiant":2022,
"tower_status_dire":0,
"barracks_status_radiant":63,
"barracks_status_dire":0,
"cluster":121,
"first_blood_time":51,
"lobby_type":7,
"human_players":10,
"leagueid":0,
"positive_votes":0,
"negative_votes":0,
"game_mode":22,
"flags":1,
"engine":1,
"radiant_score":43,
"dire_score":35
}
}