{
"result":{
"players":[
{
"account_id":4294967295,
"player_slot":0,
"hero_id":10,
"item_0":1,
"item_1":123,
"item_2":236,
"item_3":63,
"item_4":176,
"item_5":170,
"kills":13,
"deaths":2,
"assists":8,
"leaver_status":0,
"last_hits":147,
"denies":32,
"gold_per_min":613,
"xp_per_min":520,
"level":16,
"hero_damage":18719,
"tower_damage":4512,
"hero_healing":0,
"gold":251,
"gold_spent":17860,
"scaled_hero_damage":15627,
"scaled_tower_damage":3205,
"scaled_hero_healing":0,
"ability_upgrades":[
{
"ability":5055,
"time":361,
"level":1
},
{
"ability":5052,
"time":529,
"level":2
},
{
"ability":5052,
"time":583,
"level":3
},
{
"ability":5055,
"time":669,
"level":4
},
{
"ability":5052,
"time":762,
"level":5
},
{
"ability":5053,
"time":862,
"level":6
},
{
"ability":5052,
"time":954,
"level":7
},
{
"ability":5053,
"time":1087,
"level":8
},
{
"ability":5055,
"time":1188,
"level":9
},
{
"ability":5053,
"time":1361,
"level":10
},
{
"ability":5053,
"time":1398,
"level":11
},
{
"ability":5055,
"time":1614,
"level":12
},
{
"ability":5057,
"time":1656,
"level":13
},
{
"ability":5057,
"time":1875,
"level":14
},
{
"ability":5057,
"time":2123,
"level":15
},
{
"ability":5002,
"time":2124,
"level":16
}
]

},
{
"account_id":373369502,
"player_slot":1,
"hero_id":75,
"item_0":58,
"item_1":102,
"item_2":180,
"item_3":46,
"item_4":57,
"item_5":16,
"kills":4,
"deaths":2,
"assists":21,
"leaver_status":0,
"last_hits":15,
"denies":3,
"gold_per_min":335,
"xp_per_min":255,
"level":11,
"hero_damage":9417,
"tower_damage":854,
"hero_healing":0,
"gold":640,
"gold_spent":9240,
"scaled_hero_damage":8540,
"scaled_tower_damage":671,
"scaled_hero_healing":0,
"ability_upgrades":[
{
"ability":5377,
"time":404,
"level":1
},
{
"ability":5379,
"time":558,
"level":2
},
{
"ability":5377,
"time":645,
"level":3
},
{
"ability":5379,
"time":720,
"level":4
},
{
"ability":5379,
"time":854,
"level":5
},
{
"ability":5380,
"time":928,
"level":6
},
{
"ability":5379,
"time":1088,
"level":7
},
{
"ability":5378,
"time":1384,
"level":8
},
{
"ability":5378,
"time":1656,
"level":9
},
{
"ability":5378,
"time":1876,
"level":10
},
{
"ability":5380,
"time":1919,
"level":11
}
]

},
{
"account_id":320079385,
"player_slot":2,
"hero_id":29,
"item_0":90,
"item_1":180,
"item_2":119,
"item_3":46,
"item_4":0,
"item_5":1,
"kills":6,
"deaths":2,
"assists":18,
"leaver_status":0,
"last_hits":112,
"denies":8,
"gold_per_min":471,
"xp_per_min":473,
"level":16,
"hero_damage":13160,
"tower_damage":1126,
"hero_healing":0,
"gold":1259,
"gold_spent":12855,
"scaled_hero_damage":11408,
"scaled_tower_damage":697,
"scaled_hero_healing":0,
"ability_upgrades":[
{
"ability":5120,
"time":348,
"level":1
},
{
"ability":5119,
"time":555,
"level":2
},
{
"ability":5120,
"time":586,
"level":3
},
{
"ability":5119,
"time":644,
"level":4
},
{
"ability":5118,
"time":690,
"level":5
},
{
"ability":5121,
"time":777,
"level":6
},
{
"ability":5120,
"time":821,
"level":7
},
{
"ability":5120,
"time":933,
"level":8
},
{
"ability":5119,
"time":1089,
"level":9
},
{
"ability":5119,
"time":1231,
"level":10
},
{
"ability":5121,
"time":1278,
"level":11
},
{
"ability":5118,
"time":1558,
"level":12
},
{
"ability":5118,
"time":1631,
"level":13
},
{
"ability":5118,
"time":1820,
"level":14
},
{
"ability":5002,
"time":1973,
"level":15
},
{
"ability":5121,
"time":2124,
"level":16
}
]

},
{
"account_id":4294967295,
"player_slot":3,
"hero_id":4,
"item_0":127,
"item_1":242,
"item_2":63,
"item_3":114,
"item_4":0,
"item_5":0,
"kills":10,
"deaths":1,
"assists":12,
"leaver_status":0,
"last_hits":103,
"denies":2,
"gold_per_min":479,
"xp_per_min":436,
"level":15,
"hero_damage":10332,
"tower_damage":1485,
"hero_healing":1853,
"gold":430,
"gold_spent":13730,
"scaled_hero_damage":9492,
"scaled_tower_damage":1080,
"scaled_hero_healing":1373,
"ability_upgrades":[
{
"ability":5015,
"time":364,
"level":1
},
{
"ability":5017,
"time":501,
"level":2
},
{
"ability":5015,
"time":591,
"level":3
},
{
"ability":5016,
"time":648,
"level":4
},
{
"ability":5017,
"time":766,
"level":5
},
{
"ability":5018,
"time":813,
"level":6
},
{
"ability":5017,
"time":864,
"level":7
},
{
"ability":5015,
"time":1009,
"level":8
},
{
"ability":5017,
"time":1113,
"level":9
},
{
"ability":5015,
"time":1164,
"level":10
},
{
"ability":5018,
"time":1240,
"level":11
},
{
"ability":5016,
"time":1525,
"level":12
},
{
"ability":5016,
"time":1764,
"level":13
},
{
"ability":5016,
"time":1870,
"level":14
},
{
"ability":5002,
"time":2024,
"level":15
}
]

},
{
"account_id":345846547,
"player_slot":4,
"hero_id":74,
"item_0":48,
"item_1":235,
"item_2":65,
"item_3":36,
"item_4":108,
"item_5":212,
"kills":10,
"deaths":1,
"assists":14,
"leaver_status":0,
"last_hits":126,
"denies":19,
"gold_per_min":597,
"xp_per_min":547,
"level":17,
"hero_damage":9470,
"tower_damage":6029,
"hero_healing":0,
"gold":855,
"gold_spent":16545,
"scaled_hero_damage":9112,
"scaled_tower_damage":4325,
"scaled_hero_healing":0,
"ability_upgrades":[
{
"ability":5372,
"time":449,
"level":1
},
{
"ability":5370,
"time":482,
"level":2
},
{
"ability":5372,
"time":539,
"level":3
},
{
"ability":5370,
"time":566,
"level":4
},
{
"ability":5372,
"time":664,
"level":5
},
{
"ability":5370,
"time":724,
"level":6
},
{
"ability":5372,
"time":819,
"level":7
},
{
"ability":5370,
"time":931,
"level":8
},
{
"ability":5372,
"time":1088,
"level":9
},
{
"ability":5371,
"time":1183,
"level":10
},
{
"ability":5375,
"time":1232,
"level":11
},
{
"ability":5372,
"time":1513,
"level":12
},
{
"ability":5372,
"time":1660,
"level":13
},
{
"ability":5375,
"time":1758,
"level":14
},
{
"ability":5371,
"time":1879,
"level":15
},
{
"ability":5375,
"time":2039,
"level":16
},
{
"ability":5371,
"time":2075,
"level":17
}
]

},
{
"account_id":4294967295,
"player_slot":128,
"hero_id":28,
"item_0":1,
"item_1":182,
"item_2":11,
"item_3":63,
"item_4":46,
"item_5":252,
"kills":0,
"deaths":7,
"assists":2,
"leaver_status":0,
"last_hits":71,
"denies":1,
"gold_per_min":277,
"xp_per_min":277,
"level":11,
"hero_damage":2519,
"tower_damage":0,
"hero_healing":0,
"gold":496,
"gold_spent":7225,
"scaled_hero_damage":1700,
"scaled_tower_damage":0,
"scaled_hero_healing":0,
"ability_upgrades":[
{
"ability":5115,
"time":482,
"level":1
},
{
"ability":5114,
"time":572,
"level":2
},
{
"ability":5115,
"time":639,
"level":3
},
{
"ability":5116,
"time":769,
"level":4
},
{
"ability":5115,
"time":914,
"level":5
},
{
"ability":5117,
"time":1079,
"level":6
},
{
"ability":5114,
"time":1218,
"level":7
},
{
"ability":5115,
"time":1346,
"level":8
},
{
"ability":5116,
"time":1759,
"level":9
},
{
"ability":5117,
"time":2013,
"level":10
},
{
"ability":5116,
"time":2021,
"level":11
}
]

},
{
"account_id":4294967295,
"player_slot":129,
"hero_id":84,
"item_0":36,
"item_1":244,
"item_2":214,
"item_3":46,
"item_4":240,
"item_5":94,
"kills":1,
"deaths":10,
"assists":3,
"leaver_status":0,
"last_hits":10,
"denies":0,
"gold_per_min":215,
"xp_per_min":168,
"level":9,
"hero_damage":4971,
"tower_damage":0,
"hero_healing":0,
"gold":1636,
"gold_spent":3965,
"scaled_hero_damage":4459,
"scaled_tower_damage":0,
"scaled_hero_healing":0,
"ability_upgrades":[
{
"ability":5439,
"time":414,
"level":1
},
{
"ability":5438,
"time":549,
"level":2
},
{
"ability":5439,
"time":706,
"level":3
},
{
"ability":5440,
"time":891,
"level":4
},
{
"ability":5440,
"time":1039,
"level":5
},
{
"ability":5441,
"time":1498,
"level":6
},
{
"ability":5439,
"time":1659,
"level":7
},
{
"ability":5440,
"time":2145,
"level":8
}
]

},
{
"account_id":278173826,
"player_slot":130,
"hero_id":7,
"item_0":1,
"item_1":0,
"item_2":46,
"item_3":178,
"item_4":218,
"item_5":0,
"kills":0,
"deaths":13,
"assists":5,
"leaver_status":0,
"last_hits":6,
"denies":0,
"gold_per_min":238,
"xp_per_min":263,
"level":11,
"hero_damage":3773,
"tower_damage":0,
"hero_healing":0,
"gold":1193,
"gold_spent":4860,
"scaled_hero_damage":2859,
"scaled_tower_damage":0,
"scaled_hero_healing":0,
"ability_upgrades":[
{
"ability":5023,
"time":408,
"level":1
},
{
"ability":5024,
"time":552,
"level":2
},
{
"ability":5023,
"time":637,
"level":3
},
{
"ability":5025,
"time":840,
"level":4
},
{
"ability":5023,
"time":996,
"level":5
},
{
"ability":5026,
"time":1485,
"level":6
},
{
"ability":5023,
"time":1673,
"level":7
},
{
"ability":5024,
"time":2025,
"level":8
},
{
"ability":5025,
"time":2026,
"level":9
},
{
"ability":5024,
"time":2099,
"level":10
}
]

},
{
"account_id":4294967295,
"player_slot":131,
"hero_id":35,
"item_0":166,
"item_1":172,
"item_2":29,
"item_3":236,
"item_4":212,
"item_5":25,
"kills":3,
"deaths":6,
"assists":1,
"leaver_status":0,
"last_hits":101,
"denies":14,
"gold_per_min":355,
"xp_per_min":361,
"level":13,
"hero_damage":19734,
"tower_damage":47,
"hero_healing":0,
"gold":628,
"gold_spent":8960,
"scaled_hero_damage":12880,
"scaled_tower_damage":19,
"scaled_hero_healing":0,
"ability_upgrades":[
{
"ability":5154,
"time":446,
"level":1
},
{
"ability":5155,
"time":493,
"level":2
},
{
"ability":5156,
"time":560,
"level":3
},
{
"ability":5156,
"time":634,
"level":4
},
{
"ability":5154,
"time":696,
"level":5
},
{
"ability":5157,
"time":781,
"level":6
},
{
"ability":5156,
"time":871,
"level":7
},
{
"ability":5156,
"time":982,
"level":8
},
{
"ability":5155,
"time":1177,
"level":9
},
{
"ability":5155,
"time":1468,
"level":10
},
{
"ability":5157,
"time":1529,
"level":11
},
{
"ability":5155,
"time":2068,
"level":12
},
{
"ability":5154,
"time":2069,
"level":13
}
]

},
{
"account_id":4294967295,
"player_slot":132,
"hero_id":18,
"item_0":73,
"item_1":11,
"item_2":63,
"item_3":252,
"item_4":46,
"item_5":164,
"kills":2,
"deaths":8,
"assists":1,
"leaver_status":0,
"last_hits":126,
"denies":3,
"gold_per_min":343,
"xp_per_min":336,
"level":13,
"hero_damage":6273,
"tower_damage":634,
"hero_healing":0,
"gold":1822,
"gold_spent":7525,
"scaled_hero_damage":5415,
"scaled_tower_damage":542,
"scaled_hero_healing":0,
"ability_upgrades":[
{
"ability":5094,
"time":461,
"level":1
},
{
"ability":5095,
"time":510,
"level":2
},
{
"ability":5096,
"time":603,
"level":3
},
{
"ability":5096,
"time":711,
"level":4
},
{
"ability":5095,
"time":849,
"level":5
},
{
"ability":5097,
"time":1008,
"level":6
},
{
"ability":5096,
"time":1237,
"level":7
},
{
"ability":5096,
"time":1361,
"level":8
},
{
"ability":5095,
"time":1531,
"level":9
},
{
"ability":5095,
"time":1765,
"level":10
},
{
"ability":5097,
"time":1777,
"level":11
}
]

}
]
,
"radiant_win":true,
"duration":1713,
"pre_game_duration":90,
"start_time":1479736210,
"match_id":2793903041,
"match_seq_num":2437931250,
"tower_status_radiant":2046,
"tower_status_dire":4,
"barracks_status_radiant":63,
"barracks_status_dire":3,
"cluster":153,
"first_blood_time":52,
"lobby_type":7,
"human_players":10,
"leagueid":0,
"positive_votes":0,
"negative_votes":0,
"game_mode":22,
"flags":1,
"engine":1,
"radiant_score":43,
"dire_score":8
}
}