{
"result":{
"players":[
{
"account_id":177750928,
"player_slot":0,
"hero_id":107,
"item_0":36,
"item_1":214,
"item_2":1,
"item_3":92,
"item_4":0,
"item_5":46,
"kills":3,
"deaths":4,
"assists":14,
"leaver_status":0,
"last_hits":22,
"denies":2,
"gold_per_min":365,
"xp_per_min":291,
"level":12,
"hero_damage":7515,
"tower_damage":474,
"hero_healing":3600,
"gold":2546,
"gold_spent":8625,
"scaled_hero_damage":6091,
"scaled_tower_damage":339,
"scaled_hero_healing":2326,
"ability_upgrades":[
{
"ability":5609,
"time":376,
"level":1
},
{
"ability":5608,
"time":667,
"level":2
},
{
"ability":5608,
"time":727,
"level":3
},
{
"ability":5610,
"time":900,
"level":4
},
{
"ability":5608,
"time":978,
"level":5
},
{
"ability":5612,
"time":1172,
"level":6
},
{
"ability":5608,
"time":1295,
"level":7
},
{
"ability":5610,
"time":1354,
"level":8
},
{
"ability":5610,
"time":1535,
"level":9
},
{
"ability":5612,
"time":1834,
"level":10
},
{
"ability":5610,
"time":1836,
"level":11
},
{
"ability":5609,
"time":2241,
"level":12
}
]

},
{
"account_id":177535145,
"player_slot":1,
"hero_id":56,
"item_0":212,
"item_1":236,
"item_2":139,
"item_3":0,
"item_4":63,
"item_5":98,
"kills":4,
"deaths":2,
"assists":12,
"leaver_status":0,
"last_hits":159,
"denies":19,
"gold_per_min":568,
"xp_per_min":498,
"level":16,
"hero_damage":12150,
"tower_damage":12520,
"hero_healing":0,
"gold":1881,
"gold_spent":16110,
"scaled_hero_damage":11624,
"scaled_tower_damage":9040,
"scaled_hero_healing":0,
"ability_upgrades":[
{
"ability":5260,
"time":451,
"level":1
},
{
"ability":5259,
"time":539,
"level":2
},
{
"ability":5260,
"time":586,
"level":3
},
{
"ability":5261,
"time":651,
"level":4
},
{
"ability":5260,
"time":723,
"level":5
},
{
"ability":5262,
"time":786,
"level":6
},
{
"ability":5260,
"time":849,
"level":7
},
{
"ability":5259,
"time":940,
"level":8
},
{
"ability":5259,
"time":1038,
"level":9
},
{
"ability":5259,
"time":1096,
"level":10
},
{
"ability":5262,
"time":1280,
"level":11
},
{
"ability":5261,
"time":1481,
"level":12
},
{
"ability":5261,
"time":1528,
"level":13
},
{
"ability":5261,
"time":1768,
"level":14
},
{
"ability":5002,
"time":1920,
"level":15
},
{
"ability":5262,
"time":2029,
"level":16
}
]

},
{
"account_id":197775585,
"player_slot":2,
"hero_id":73,
"item_0":151,
"item_1":166,
"item_2":147,
"item_3":48,
"item_4":235,
"item_5":137,
"kills":6,
"deaths":1,
"assists":8,
"leaver_status":0,
"last_hits":222,
"denies":0,
"gold_per_min":850,
"xp_per_min":626,
"level":18,
"hero_damage":15216,
"tower_damage":4634,
"hero_healing":0,
"gold":1395,
"gold_spent":24715,
"scaled_hero_damage":11069,
"scaled_tower_damage":3275,
"scaled_hero_healing":0,
"ability_upgrades":[
{
"ability":5368,
"time":394,
"level":1
},
{
"ability":5365,
"time":523,
"level":2
},
{
"ability":5365,
"time":553,
"level":3
},
{
"ability":5368,
"time":628,
"level":4
},
{
"ability":5365,
"time":695,
"level":5
},
{
"ability":5369,
"time":795,
"level":6
},
{
"ability":5368,
"time":859,
"level":7
},
{
"ability":5368,
"time":1017,
"level":8
},
{
"ability":5365,
"time":1171,
"level":9
},
{
"ability":5366,
"time":1302,
"level":10
},
{
"ability":5369,
"time":1349,
"level":11
},
{
"ability":5366,
"time":1567,
"level":12
},
{
"ability":5366,
"time":1594,
"level":13
},
{
"ability":5366,
"time":1731,
"level":14
},
{
"ability":5002,
"time":1882,
"level":15
},
{
"ability":5369,
"time":1922,
"level":16
},
{
"ability":5002,
"time":1947,
"level":17
},
{
"ability":5002,
"time":2134,
"level":18
}
]

},
{
"account_id":4294967295,
"player_slot":3,
"hero_id":22,
"item_0":180,
"item_1":1,
"item_2":46,
"item_3":108,
"item_4":232,
"item_5":0,
"kills":8,
"deaths":2,
"assists":7,
"leaver_status":0,
"last_hits":77,
"denies":1,
"gold_per_min":469,
"xp_per_min":494,
"level":16,
"hero_damage":26364,
"tower_damage":292,
"hero_healing":0,
"gold":3096,
"gold_spent":12125,
"scaled_hero_damage":17384,
"scaled_tower_damage":197,
"scaled_hero_healing":0,
"ability_upgrades":[
{
"ability":5110,
"time":381,
"level":1
},
{
"ability":5111,
"time":506,
"level":2
},
{
"ability":5111,
"time":580,
"level":3
},
{
"ability":5002,
"time":656,
"level":4
},
{
"ability":5111,
"time":728,
"level":5
},
{
"ability":5113,
"time":808,
"level":6
},
{
"ability":5111,
"time":931,
"level":7
},
{
"ability":5112,
"time":1043,
"level":8
},
{
"ability":5112,
"time":1150,
"level":9
},
{
"ability":5112,
"time":1250,
"level":10
},
{
"ability":5113,
"time":1327,
"level":11
},
{
"ability":5112,
"time":1730,
"level":12
},
{
"ability":5110,
"time":1829,
"level":13
},
{
"ability":5110,
"time":1925,
"level":14
},
{
"ability":5110,
"time":2016,
"level":15
},
{
"ability":5113,
"time":2173,
"level":16
}
]

},
{
"account_id":114762298,
"player_slot":4,
"hero_id":7,
"item_0":1,
"item_1":244,
"item_2":180,
"item_3":46,
"item_4":36,
"item_5":178,
"kills":5,
"deaths":3,
"assists":9,
"leaver_status":0,
"last_hits":48,
"denies":2,
"gold_per_min":393,
"xp_per_min":316,
"level":13,
"hero_damage":8318,
"tower_damage":860,
"hero_healing":0,
"gold":1264,
"gold_spent":10645,
"scaled_hero_damage":6641,
"scaled_tower_damage":682,
"scaled_hero_healing":0,
"ability_upgrades":[
{
"ability":5023,
"time":407,
"level":1
},
{
"ability":5024,
"time":640,
"level":2
},
{
"ability":5025,
"time":723,
"level":3
},
{
"ability":5023,
"time":832,
"level":4
},
{
"ability":5023,
"time":1069,
"level":5
},
{
"ability":5026,
"time":1163,
"level":6
},
{
"ability":5023,
"time":1228,
"level":7
},
{
"ability":5025,
"time":1345,
"level":8
},
{
"ability":5025,
"time":1478,
"level":9
},
{
"ability":5025,
"time":1527,
"level":10
},
{
"ability":5026,
"time":1688,
"level":11
},
{
"ability":5024,
"time":2122,
"level":12
},
{
"ability":5024,
"time":2228,
"level":13
}
]

},
{
"account_id":4294967295,
"player_slot":128,
"hero_id":80,
"item_0":46,
"item_1":16,
"item_2":16,
"item_3":182,
"item_4":214,
"item_5":0,
"kills":2,
"deaths":8,
"assists":4,
"leaver_status":0,
"last_hits":80,
"denies":3,
"gold_per_min":310,
"xp_per_min":359,
"level":14,
"hero_damage":7290,
"tower_damage":791,
"hero_healing":0,
"gold":461,
"gold_spent":8350,
"scaled_hero_damage":5597,
"scaled_tower_damage":520,
"scaled_hero_healing":0,
"ability_upgrades":[
{
"ability":5412,
"time":372,
"level":1
},
{
"ability":5413,
"time":549,
"level":2
},
{
"ability":5412,
"time":610,
"level":3
},
{
"ability":5413,
"time":684,
"level":4
},
{
"ability":5412,
"time":799,
"level":5
},
{
"ability":5415,
"time":908,
"level":6
},
{
"ability":5412,
"time":994,
"level":7
},
{
"ability":5413,
"time":1149,
"level":8
},
{
"ability":5413,
"time":1295,
"level":9
},
{
"ability":5414,
"time":1534,
"level":10
},
{
"ability":5416,
"time":1557,
"level":11
},
{
"ability":5414,
"time":1820,
"level":12
},
{
"ability":5414,
"time":1875,
"level":13
},
{
"ability":5414,
"time":2078,
"level":14
}
]
,
"additional_units":[
{
"unitname":"spirit_bear",
"item_0":11,
"item_1":166,
"item_2":181,
"item_3":29,
"item_4":65,
"item_5":182
}
]

},
{
"account_id":324741797,
"player_slot":129,
"hero_id":89,
"item_0":212,
"item_1":48,
"item_2":11,
"item_3":137,
"item_4":71,
"item_5":59,
"kills":0,
"deaths":3,
"assists":4,
"leaver_status":0,
"last_hits":224,
"denies":7,
"gold_per_min":366,
"xp_per_min":286,
"level":12,
"hero_damage":8298,
"tower_damage":42,
"hero_healing":0,
"gold":156,
"gold_spent":10610,
"scaled_hero_damage":3585,
"scaled_tower_damage":14,
"scaled_hero_healing":0,
"ability_upgrades":[
{
"ability":5469,
"time":545,
"level":1
},
{
"ability":5467,
"time":604,
"level":2
},
{
"ability":5469,
"time":626,
"level":3
},
{
"ability":5467,
"time":673,
"level":4
},
{
"ability":5469,
"time":742,
"level":5
},
{
"ability":5467,
"time":828,
"level":6
},
{
"ability":5469,
"time":894,
"level":7
},
{
"ability":5467,
"time":1147,
"level":8
},
{
"ability":5470,
"time":1260,
"level":9
},
{
"ability":5002,
"time":1508,
"level":10
},
{
"ability":5470,
"time":1631,
"level":11
},
{
"ability":5468,
"time":2008,
"level":12
}
]

},
{
"account_id":4294967295,
"player_slot":130,
"hero_id":9,
"item_0":180,
"item_1":108,
"item_2":212,
"item_3":46,
"item_4":0,
"item_5":0,
"kills":6,
"deaths":6,
"assists":3,
"leaver_status":0,
"last_hits":80,
"denies":0,
"gold_per_min":311,
"xp_per_min":301,
"level":13,
"hero_damage":8898,
"tower_damage":0,
"hero_healing":0,
"gold":146,
"gold_spent":7680,
"scaled_hero_damage":6406,
"scaled_tower_damage":0,
"scaled_hero_healing":0,
"ability_upgrades":[
{
"ability":5048,
"time":371,
"level":1
},
{
"ability":5050,
"time":600,
"level":2
},
{
"ability":5051,
"time":682,
"level":3
},
{
"ability":5051,
"time":764,
"level":4
},
{
"ability":5051,
"time":968,
"level":5
},
{
"ability":5050,
"time":1101,
"level":6
},
{
"ability":5051,
"time":1178,
"level":7
},
{
"ability":5048,
"time":1296,
"level":8
},
{
"ability":5049,
"time":1456,
"level":9
},
{
"ability":5050,
"time":1588,
"level":10
},
{
"ability":5049,
"time":1682,
"level":11
},
{
"ability":5050,
"time":1866,
"level":12
},
{
"ability":5048,
"time":2198,
"level":13
}
]

},
{
"account_id":154723688,
"player_slot":131,
"hero_id":76,
"item_0":41,
"item_1":46,
"item_2":263,
"item_3":29,
"item_4":0,
"item_5":0,
"kills":1,
"deaths":7,
"assists":5,
"leaver_status":0,
"last_hits":90,
"denies":10,
"gold_per_min":274,
"xp_per_min":307,
"level":13,
"hero_damage":10877,
"tower_damage":68,
"hero_healing":0,
"gold":953,
"gold_spent":6765,
"scaled_hero_damage":7197,
"scaled_tower_damage":38,
"scaled_hero_healing":0,
"ability_upgrades":[
{
"ability":5392,
"time":402,
"level":1
},
{
"ability":5393,
"time":520,
"level":2
},
{
"ability":5392,
"time":562,
"level":3
},
{
"ability":5391,
"time":619,
"level":4
},
{
"ability":5392,
"time":739,
"level":5
},
{
"ability":5393,
"time":843,
"level":6
},
{
"ability":5392,
"time":938,
"level":7
},
{
"ability":5391,
"time":1061,
"level":8
},
{
"ability":5393,
"time":1179,
"level":9
},
{
"ability":5394,
"time":1348,
"level":10
},
{
"ability":5394,
"time":1555,
"level":11
},
{
"ability":5393,
"time":1902,
"level":12
},
{
"ability":5391,
"time":2075,
"level":13
}
]

},
{
"account_id":71918782,
"player_slot":132,
"hero_id":86,
"item_0":232,
"item_1":178,
"item_2":244,
"item_3":214,
"item_4":30,
"item_5":46,
"kills":2,
"deaths":2,
"assists":8,
"leaver_status":0,
"last_hits":67,
"denies":2,
"gold_per_min":284,
"xp_per_min":335,
"level":13,
"hero_damage":12436,
"tower_damage":0,
"hero_healing":0,
"gold":880,
"gold_spent":7405,
"scaled_hero_damage":6728,
"scaled_tower_damage":0,
"scaled_hero_healing":0,
"ability_upgrades":[
{
"ability":5448,
"time":381,
"level":1
},
{
"ability":5450,
"time":517,
"level":2
},
{
"ability":5450,
"time":589,
"level":3
},
{
"ability":5448,
"time":716,
"level":4
},
{
"ability":5450,
"time":846,
"level":5
},
{
"ability":5452,
"time":997,
"level":6
},
{
"ability":5450,
"time":1071,
"level":7
},
{
"ability":5448,
"time":1211,
"level":8
},
{
"ability":5451,
"time":1531,
"level":9
},
{
"ability":5448,
"time":1560,
"level":10
},
{
"ability":5452,
"time":1664,
"level":11
},
{
"ability":5451,
"time":1782,
"level":12
},
{
"ability":5451,
"time":1859,
"level":13
}
]

}
]
,
"radiant_win":true,
"duration":1809,
"pre_game_duration":90,
"start_time":1479797727,
"match_id":2795206876,
"match_seq_num":2439076041,
"tower_status_radiant":1983,
"tower_status_dire":0,
"barracks_status_radiant":63,
"barracks_status_dire":0,
"cluster":154,
"first_blood_time":130,
"lobby_type":7,
"human_players":10,
"leagueid":0,
"positive_votes":0,
"negative_votes":0,
"game_mode":22,
"flags":1,
"engine":1,
"radiant_score":26,
"dire_score":12
}
}