{
"result":{
"players":[
{
"account_id":329487545,
"player_slot":0,
"hero_id":73,
"item_0":9,
"item_1":11,
"item_2":9,
"item_3":137,
"item_4":48,
"item_5":235,
"kills":0,
"deaths":9,
"assists":4,
"leaver_status":0,
"last_hits":226,
"denies":3,
"gold_per_min":563,
"xp_per_min":487,
"level":18,
"hero_damage":7688,
"tower_damage":269,
"hero_healing":0,
"gold":337,
"gold_spent":17775,
"scaled_hero_damage":4974,
"scaled_tower_damage":285,
"scaled_hero_healing":0,
"ability_upgrades":[
{
"ability":5365,
"time":189,
"level":1
},
{
"ability":5368,
"time":231,
"level":2
},
{
"ability":5365,
"time":294,
"level":3
},
{
"ability":5368,
"time":354,
"level":4
},
{
"ability":5368,
"time":438,
"level":5
},
{
"ability":5369,
"time":498,
"level":6
},
{
"ability":5368,
"time":556,
"level":7
},
{
"ability":5365,
"time":665,
"level":8
},
{
"ability":5365,
"time":761,
"level":9
},
{
"ability":5366,
"time":868,
"level":10
},
{
"ability":5369,
"time":910,
"level":11
},
{
"ability":5366,
"time":1176,
"level":12
},
{
"ability":5366,
"time":1226,
"level":13
},
{
"ability":5366,
"time":1309,
"level":14
},
{
"ability":5002,
"time":1464,
"level":15
},
{
"ability":5369,
"time":1653,
"level":16
},
{
"ability":5002,
"time":1890,
"level":17
},
{
"ability":5002,
"time":2216,
"level":18
}
]

},
{
"account_id":303521870,
"player_slot":1,
"hero_id":63,
"item_0":92,
"item_1":212,
"item_2":63,
"item_3":168,
"item_4":36,
"item_5":0,
"kills":6,
"deaths":13,
"assists":5,
"leaver_status":0,
"last_hits":93,
"denies":4,
"gold_per_min":366,
"xp_per_min":459,
"level":17,
"hero_damage":14846,
"tower_damage":148,
"hero_healing":0,
"gold":2467,
"gold_spent":8850,
"scaled_hero_damage":11764,
"scaled_tower_damage":122,
"scaled_hero_healing":0,
"ability_upgrades":[
{
"ability":5290,
"time":126,
"level":1
},
{
"ability":5291,
"time":290,
"level":2
},
{
"ability":5290,
"time":312,
"level":3
},
{
"ability":5289,
"time":436,
"level":4
},
{
"ability":5290,
"time":522,
"level":5
},
{
"ability":5292,
"time":638,
"level":6
},
{
"ability":5290,
"time":711,
"level":7
},
{
"ability":5289,
"time":887,
"level":8
},
{
"ability":5289,
"time":1114,
"level":9
},
{
"ability":5289,
"time":1220,
"level":10
},
{
"ability":5292,
"time":1313,
"level":11
},
{
"ability":5291,
"time":1561,
"level":12
},
{
"ability":5291,
"time":1585,
"level":13
},
{
"ability":5291,
"time":1785,
"level":14
},
{
"ability":5002,
"time":1786,
"level":15
},
{
"ability":5292,
"time":2143,
"level":16
},
{
"ability":5002,
"time":2143,
"level":17
}
]

},
{
"account_id":200888038,
"player_slot":2,
"hero_id":75,
"item_0":65,
"item_1":46,
"item_2":21,
"item_3":0,
"item_4":0,
"item_5":29,
"kills":1,
"deaths":16,
"assists":3,
"leaver_status":0,
"last_hits":38,
"denies":11,
"gold_per_min":190,
"xp_per_min":171,
"level":11,
"hero_damage":5141,
"tower_damage":0,
"hero_healing":0,
"gold":294,
"gold_spent":5095,
"scaled_hero_damage":4317,
"scaled_tower_damage":0,
"scaled_hero_healing":0,
"ability_upgrades":[
{
"ability":5378,
"time":121,
"level":1
},
{
"ability":5377,
"time":305,
"level":2
},
{
"ability":5377,
"time":382,
"level":3
},
{
"ability":5379,
"time":432,
"level":4
},
{
"ability":5377,
"time":487,
"level":5
},
{
"ability":5380,
"time":579,
"level":6
},
{
"ability":5377,
"time":994,
"level":7
},
{
"ability":5379,
"time":1515,
"level":8
},
{
"ability":5379,
"time":1829,
"level":9
},
{
"ability":5379,
"time":2017,
"level":10
},
{
"ability":5380,
"time":2224,
"level":11
}
]

},
{
"account_id":101804476,
"player_slot":3,
"hero_id":44,
"item_0":145,
"item_1":81,
"item_2":0,
"item_3":21,
"item_4":63,
"item_5":240,
"kills":2,
"deaths":10,
"assists":4,
"leaver_status":0,
"last_hits":170,
"denies":5,
"gold_per_min":364,
"xp_per_min":453,
"level":17,
"hero_damage":6834,
"tower_damage":95,
"hero_healing":120,
"gold":130,
"gold_spent":11650,
"scaled_hero_damage":5346,
"scaled_tower_damage":49,
"scaled_hero_healing":64,
"ability_upgrades":[
{
"ability":5190,
"time":146,
"level":1
},
{
"ability":5191,
"time":313,
"level":2
},
{
"ability":5190,
"time":339,
"level":3
},
{
"ability":5191,
"time":455,
"level":4
},
{
"ability":5191,
"time":576,
"level":5
},
{
"ability":5193,
"time":664,
"level":6
},
{
"ability":5190,
"time":785,
"level":7
},
{
"ability":5190,
"time":887,
"level":8
},
{
"ability":5192,
"time":1008,
"level":9
},
{
"ability":5191,
"time":1158,
"level":10
},
{
"ability":5193,
"time":1241,
"level":11
},
{
"ability":5192,
"time":1767,
"level":12
},
{
"ability":5192,
"time":1771,
"level":13
},
{
"ability":5192,
"time":1771,
"level":14
},
{
"ability":5002,
"time":1839,
"level":15
},
{
"ability":5193,
"time":2024,
"level":16
},
{
"ability":5002,
"time":2148,
"level":17
}
]

},
{
"account_id":155755258,
"player_slot":4,
"hero_id":34,
"item_0":232,
"item_1":48,
"item_2":178,
"item_3":41,
"item_4":108,
"item_5":1,
"kills":4,
"deaths":4,
"assists":4,
"leaver_status":0,
"last_hits":195,
"denies":0,
"gold_per_min":404,
"xp_per_min":449,
"level":17,
"hero_damage":28085,
"tower_damage":0,
"hero_healing":0,
"gold":545,
"gold_spent":13865,
"scaled_hero_damage":13098,
"scaled_tower_damage":0,
"scaled_hero_healing":0,
"ability_upgrades":[
{
"ability":5152,
"time":210,
"level":1
},
{
"ability":5150,
"time":255,
"level":2
},
{
"ability":5152,
"time":303,
"level":3
},
{
"ability":5150,
"time":388,
"level":4
},
{
"ability":5152,
"time":460,
"level":5
},
{
"ability":5153,
"time":613,
"level":6
},
{
"ability":5152,
"time":680,
"level":7
},
{
"ability":5150,
"time":835,
"level":8
},
{
"ability":5151,
"time":906,
"level":9
},
{
"ability":5150,
"time":1017,
"level":10
},
{
"ability":5151,
"time":1068,
"level":11
},
{
"ability":5151,
"time":1378,
"level":12
},
{
"ability":5151,
"time":1592,
"level":13
},
{
"ability":5002,
"time":1754,
"level":14
},
{
"ability":5153,
"time":1960,
"level":15
},
{
"ability":5153,
"time":2141,
"level":16
},
{
"ability":5002,
"time":2142,
"level":17
}
]

},
{
"account_id":144440590,
"player_slot":128,
"hero_id":18,
"item_0":1,
"item_1":116,
"item_2":141,
"item_3":48,
"item_4":252,
"item_5":156,
"kills":16,
"deaths":3,
"assists":14,
"leaver_status":0,
"last_hits":351,
"denies":4,
"gold_per_min":880,
"xp_per_min":907,
"level":25,
"hero_damage":29575,
"tower_damage":13037,
"hero_healing":0,
"gold":6948,
"gold_spent":27820,
"scaled_hero_damage":20243,
"scaled_tower_damage":9411,
"scaled_hero_healing":0,
"ability_upgrades":[
{
"ability":5094,
"time":131,
"level":1
},
{
"ability":5096,
"time":272,
"level":2
},
{
"ability":5095,
"time":361,
"level":3
},
{
"ability":5095,
"time":489,
"level":4
},
{
"ability":5095,
"time":552,
"level":5
},
{
"ability":5097,
"time":658,
"level":6
},
{
"ability":5095,
"time":743,
"level":7
},
{
"ability":5096,
"time":817,
"level":8
},
{
"ability":5096,
"time":946,
"level":9
},
{
"ability":5096,
"time":1020,
"level":10
},
{
"ability":5097,
"time":1074,
"level":11
},
{
"ability":5094,
"time":1177,
"level":12
},
{
"ability":5094,
"time":1273,
"level":13
},
{
"ability":5094,
"time":1372,
"level":14
},
{
"ability":5002,
"time":1450,
"level":15
},
{
"ability":5097,
"time":1501,
"level":16
},
{
"ability":5002,
"time":1581,
"level":17
},
{
"ability":5002,
"time":1629,
"level":18
},
{
"ability":5002,
"time":1705,
"level":19
},
{
"ability":5002,
"time":1771,
"level":20
},
{
"ability":5002,
"time":1802,
"level":21
},
{
"ability":5002,
"time":1898,
"level":22
},
{
"ability":5002,
"time":2078,
"level":23
},
{
"ability":5002,
"time":2193,
"level":24
},
{
"ability":5002,
"time":2280,
"level":25
}
]

},
{
"account_id":136484837,
"player_slot":129,
"hero_id":26,
"item_0":100,
"item_1":254,
"item_2":1,
"item_3":46,
"item_4":214,
"item_5":0,
"kills":8,
"deaths":5,
"assists":16,
"leaver_status":0,
"last_hits":18,
"denies":0,
"gold_per_min":387,
"xp_per_min":466,
"level":17,
"hero_damage":8417,
"tower_damage":190,
"hero_healing":0,
"gold":3200,
"gold_spent":10845,
"scaled_hero_damage":7499,
"scaled_tower_damage":133,
"scaled_hero_healing":0,
"ability_upgrades":[
{
"ability":5044,
"time":221,
"level":1
},
{
"ability":5045,
"time":344,
"level":2
},
{
"ability":5044,
"time":471,
"level":3
},
{
"ability":5046,
"time":602,
"level":4
},
{
"ability":5044,
"time":687,
"level":5
},
{
"ability":5047,
"time":871,
"level":6
},
{
"ability":5044,
"time":1016,
"level":7
},
{
"ability":5046,
"time":1256,
"level":8
},
{
"ability":5046,
"time":1366,
"level":9
},
{
"ability":5046,
"time":1473,
"level":10
},
{
"ability":5047,
"time":1549,
"level":11
},
{
"ability":5045,
"time":1861,
"level":12
},
{
"ability":5045,
"time":1919,
"level":13
},
{
"ability":5045,
"time":2026,
"level":14
},
{
"ability":5002,
"time":2055,
"level":15
},
{
"ability":5047,
"time":2126,
"level":16
},
{
"ability":5002,
"time":2267,
"level":17
}
]

},
{
"account_id":350850160,
"player_slot":130,
"hero_id":74,
"item_0":1,
"item_1":100,
"item_2":48,
"item_3":123,
"item_4":235,
"item_5":108,
"kills":16,
"deaths":1,
"assists":8,
"leaver_status":0,
"last_hits":269,
"denies":13,
"gold_per_min":802,
"xp_per_min":831,
"level":24,
"hero_damage":19385,
"tower_damage":6422,
"hero_healing":0,
"gold":5303,
"gold_spent":25190,
"scaled_hero_damage":15907,
"scaled_tower_damage":4503,
"scaled_hero_healing":0,
"ability_upgrades":[
{
"ability":5372,
"time":167,
"level":1
},
{
"ability":5371,
"time":242,
"level":2
},
{
"ability":5370,
"time":306,
"level":3
},
{
"ability":5372,
"time":361,
"level":4
},
{
"ability":5370,
"time":419,
"level":5
},
{
"ability":5370,
"time":488,
"level":6
},
{
"ability":5372,
"time":571,
"level":7
},
{
"ability":5372,
"time":639,
"level":8
},
{
"ability":5370,
"time":752,
"level":9
},
{
"ability":5372,
"time":851,
"level":10
},
{
"ability":5375,
"time":941,
"level":11
},
{
"ability":5372,
"time":1212,
"level":12
},
{
"ability":5375,
"time":1267,
"level":13
},
{
"ability":5372,
"time":1334,
"level":14
},
{
"ability":5371,
"time":1462,
"level":15
},
{
"ability":5375,
"time":1523,
"level":16
},
{
"ability":5371,
"time":1773,
"level":17
},
{
"ability":5371,
"time":1776,
"level":18
},
{
"ability":5370,
"time":1931,
"level":19
},
{
"ability":5371,
"time":2027,
"level":20
},
{
"ability":5370,
"time":2090,
"level":21
},
{
"ability":5370,
"time":2222,
"level":22
}
]

},
{
"account_id":350514630,
"player_slot":131,
"hero_id":107,
"item_0":92,
"item_1":180,
"item_2":79,
"item_3":1,
"item_4":254,
"item_5":30,
"kills":3,
"deaths":3,
"assists":30,
"leaver_status":0,
"last_hits":46,
"denies":1,
"gold_per_min":393,
"xp_per_min":507,
"level":18,
"hero_damage":12057,
"tower_damage":273,
"hero_healing":3466,
"gold":3138,
"gold_spent":11255,
"scaled_hero_damage":9878,
"scaled_tower_damage":220,
"scaled_hero_healing":1620,
"ability_upgrades":[
{
"ability":5609,
"time":116,
"level":1
},
{
"ability":5608,
"time":272,
"level":2
},
{
"ability":5610,
"time":355,
"level":3
},
{
"ability":5608,
"time":511,
"level":4
},
{
"ability":5610,
"time":656,
"level":5
},
{
"ability":5612,
"time":778,
"level":6
},
{
"ability":5608,
"time":1051,
"level":7
},
{
"ability":5608,
"time":1134,
"level":8
},
{
"ability":5610,
"time":1193,
"level":9
},
{
"ability":5610,
"time":1368,
"level":10
},
{
"ability":5609,
"time":1415,
"level":11
},
{
"ability":5612,
"time":1581,
"level":12
},
{
"ability":5609,
"time":1666,
"level":13
},
{
"ability":5609,
"time":1862,
"level":14
},
{
"ability":5002,
"time":1941,
"level":15
},
{
"ability":5612,
"time":2061,
"level":16
},
{
"ability":5002,
"time":2166,
"level":17
},
{
"ability":5002,
"time":2282,
"level":18
}
]

},
{
"account_id":90153633,
"player_slot":132,
"hero_id":88,
"item_0":1,
"item_1":201,
"item_2":46,
"item_3":108,
"item_4":180,
"item_5":65,
"kills":6,
"deaths":4,
"assists":18,
"leaver_status":0,
"last_hits":82,
"denies":13,
"gold_per_min":462,
"xp_per_min":567,
"level":19,
"hero_damage":15832,
"tower_damage":193,
"hero_healing":0,
"gold":1107,
"gold_spent":15980,
"scaled_hero_damage":12187,
"scaled_tower_damage":115,
"scaled_hero_healing":0,
"ability_upgrades":[
{
"ability":5463,
"time":232,
"level":1
},
{
"ability":5462,
"time":267,
"level":2
},
{
"ability":5464,
"time":358,
"level":3
},
{
"ability":5462,
"time":431,
"level":4
},
{
"ability":5462,
"time":511,
"level":5
},
{
"ability":5465,
"time":588,
"level":6
},
{
"ability":5462,
"time":611,
"level":7
},
{
"ability":5464,
"time":738,
"level":8
},
{
"ability":5463,
"time":925,
"level":9
},
{
"ability":5463,
"time":1079,
"level":10
},
{
"ability":5465,
"time":1084,
"level":11
},
{
"ability":5463,
"time":1213,
"level":12
},
{
"ability":5464,
"time":1302,
"level":13
},
{
"ability":5464,
"time":1379,
"level":14
},
{
"ability":5002,
"time":1466,
"level":15
},
{
"ability":5465,
"time":1683,
"level":16
},
{
"ability":5002,
"time":1925,
"level":17
},
{
"ability":5002,
"time":2153,
"level":18
},
{
"ability":5002,
"time":2289,
"level":19
}
]

}
]
,
"radiant_win":false,
"duration":2158,
"pre_game_duration":90,
"start_time":1479641845,
"match_id":2791477091,
"match_seq_num":2435818835,
"tower_status_radiant":0,
"tower_status_dire":1974,
"barracks_status_radiant":0,
"barracks_status_dire":63,
"cluster":223,
"first_blood_time":49,
"lobby_type":0,
"human_players":10,
"leagueid":0,
"positive_votes":0,
"negative_votes":0,
"game_mode":4,
"flags":1,
"engine":1,
"radiant_score":14,
"dire_score":51
}
}