{
"result":{
"players":[
{
"account_id":150448392,
"player_slot":0,
"hero_id":88,
"item_0":46,
"item_1":204,
"item_2":71,
"item_3":180,
"item_4":0,
"item_5":16,
"kills":4,
"deaths":0,
"assists":8,
"leaver_status":0,
"last_hits":61,
"denies":13,
"gold_per_min":509,
"xp_per_min":362,
"level":11,
"hero_damage":6653,
"tower_damage":897,
"hero_healing":0,
"gold":1045,
"gold_spent":10595,
"scaled_hero_damage":6119,
"scaled_tower_damage":664,
"scaled_hero_healing":0,
"ability_upgrades":[
{
"ability":5462,
"time":395,
"level":1
},
{
"ability":5464,
"time":461,
"level":2
},
{
"ability":5463,
"time":557,
"level":3
},
{
"ability":5462,
"time":636,
"level":4
},
{
"ability":5462,
"time":696,
"level":5
},
{
"ability":5465,
"time":769,
"level":6
},
{
"ability":5462,
"time":903,
"level":7
},
{
"ability":5463,
"time":1011,
"level":8
},
{
"ability":5463,
"time":1126,
"level":9
},
{
"ability":5463,
"time":1246,
"level":10
},
{
"ability":5465,
"time":1327,
"level":11
}
]

},
{
"account_id":375223839,
"player_slot":1,
"hero_id":17,
"item_0":63,
"item_1":77,
"item_2":41,
"item_3":67,
"item_4":46,
"item_5":121,
"kills":8,
"deaths":3,
"assists":5,
"leaver_status":0,
"last_hits":119,
"denies":4,
"gold_per_min":652,
"xp_per_min":542,
"level":14,
"hero_damage":10202,
"tower_damage":268,
"hero_healing":0,
"gold":4364,
"gold_spent":9705,
"scaled_hero_damage":10350,
"scaled_tower_damage":199,
"scaled_hero_healing":0,
"ability_upgrades":[
{
"ability":5098,
"time":283,
"level":1
},
{
"ability":5100,
"time":413,
"level":2
},
{
"ability":5100,
"time":459,
"level":3
},
{
"ability":5098,
"time":533,
"level":4
},
{
"ability":5100,
"time":580,
"level":5
},
{
"ability":5101,
"time":669,
"level":6
},
{
"ability":5100,
"time":710,
"level":7
},
{
"ability":5098,
"time":844,
"level":8
},
{
"ability":5098,
"time":928,
"level":9
},
{
"ability":5099,
"time":981,
"level":10
},
{
"ability":5101,
"time":1044,
"level":11
},
{
"ability":5099,
"time":1242,
"level":12
},
{
"ability":5099,
"time":1328,
"level":13
},
{
"ability":5099,
"time":1416,
"level":14
}
]

},
{
"account_id":137036934,
"player_slot":2,
"hero_id":10,
"item_0":212,
"item_1":63,
"item_2":176,
"item_3":46,
"item_4":123,
"item_5":0,
"kills":3,
"deaths":2,
"assists":1,
"leaver_status":0,
"last_hits":101,
"denies":18,
"gold_per_min":565,
"xp_per_min":363,
"level":11,
"hero_damage":3205,
"tower_damage":5397,
"hero_healing":0,
"gold":380,
"gold_spent":12160,
"scaled_hero_damage":2901,
"scaled_tower_damage":3699,
"scaled_hero_healing":0,
"ability_upgrades":[
{
"ability":5055,
"time":288,
"level":1
},
{
"ability":5052,
"time":428,
"level":2
},
{
"ability":5055,
"time":522,
"level":3
},
{
"ability":5052,
"time":673,
"level":4
},
{
"ability":5052,
"time":787,
"level":5
},
{
"ability":5055,
"time":895,
"level":6
},
{
"ability":5052,
"time":974,
"level":7
},
{
"ability":5057,
"time":1033,
"level":8
},
{
"ability":5055,
"time":1229,
"level":9
},
{
"ability":5053,
"time":1326,
"level":10
},
{
"ability":5057,
"time":1428,
"level":11
}
]

},
{
"account_id":138653677,
"player_slot":3,
"hero_id":59,
"item_0":202,
"item_1":151,
"item_2":29,
"item_3":36,
"item_4":46,
"item_5":164,
"kills":4,
"deaths":4,
"assists":7,
"leaver_status":0,
"last_hits":53,
"denies":2,
"gold_per_min":512,
"xp_per_min":297,
"level":11,
"hero_damage":9927,
"tower_damage":7284,
"hero_healing":0,
"gold":373,
"gold_spent":11030,
"scaled_hero_damage":9142,
"scaled_tower_damage":5327,
"scaled_hero_healing":0,
"ability_upgrades":[
{
"ability":5272,
"time":307,
"level":1
},
{
"ability":5273,
"time":460,
"level":2
},
{
"ability":5272,
"time":555,
"level":3
},
{
"ability":5271,
"time":639,
"level":4
},
{
"ability":5272,
"time":833,
"level":5
},
{
"ability":5274,
"time":909,
"level":6
},
{
"ability":5272,
"time":1031,
"level":7
},
{
"ability":5273,
"time":1223,
"level":8
},
{
"ability":5273,
"time":1309,
"level":9
},
{
"ability":5273,
"time":1465,
"level":10
},
{
"ability":5271,
"time":1485,
"level":11
}
]

},
{
"account_id":166063810,
"player_slot":4,
"hero_id":23,
"item_0":46,
"item_1":60,
"item_2":11,
"item_3":92,
"item_4":180,
"item_5":37,
"kills":3,
"deaths":0,
"assists":8,
"leaver_status":0,
"last_hits":30,
"denies":0,
"gold_per_min":446,
"xp_per_min":339,
"level":11,
"hero_damage":3059,
"tower_damage":525,
"hero_healing":1637,
"gold":373,
"gold_spent":11455,
"scaled_hero_damage":2495,
"scaled_tower_damage":359,
"scaled_hero_healing":1333,
"ability_upgrades":[
{
"ability":5031,
"time":288,
"level":1
},
{
"ability":5033,
"time":460,
"level":2
},
{
"ability":5033,
"time":521,
"level":3
},
{
"ability":5031,
"time":691,
"level":4
},
{
"ability":5033,
"time":826,
"level":5
},
{
"ability":5035,
"time":980,
"level":6
},
{
"ability":5033,
"time":1117,
"level":7
},
{
"ability":5031,
"time":1225,
"level":8
},
{
"ability":5032,
"time":1306,
"level":9
},
{
"ability":5031,
"time":1405,
"level":10
},
{
"ability":5035,
"time":1420,
"level":11
}
]

},
{
"account_id":203566068,
"player_slot":128,
"hero_id":84,
"item_0":180,
"item_1":46,
"item_2":36,
"item_3":0,
"item_4":244,
"item_5":12,
"kills":2,
"deaths":3,
"assists":3,
"leaver_status":0,
"last_hits":23,
"denies":4,
"gold_per_min":235,
"xp_per_min":204,
"level":9,
"hero_damage":1859,
"tower_damage":0,
"hero_healing":0,
"gold":2169,
"gold_spent":3220,
"scaled_hero_damage":2135,
"scaled_tower_damage":0,
"scaled_hero_healing":0,
"ability_upgrades":[
{
"ability":5439,
"time":419,
"level":1
},
{
"ability":5438,
"time":518,
"level":2
},
{
"ability":5440,
"time":590,
"level":3
},
{
"ability":5440,
"time":656,
"level":4
},
{
"ability":5440,
"time":756,
"level":5
},
{
"ability":5441,
"time":912,
"level":6
},
{
"ability":5002,
"time":1057,
"level":7
},
{
"ability":5440,
"time":1379,
"level":8
}
]

},
{
"account_id":147323976,
"player_slot":129,
"hero_id":101,
"item_0":44,
"item_1":215,
"item_2":0,
"item_3":29,
"item_4":34,
"item_5":0,
"kills":1,
"deaths":6,
"assists":1,
"leaver_status":0,
"last_hits":2,
"denies":0,
"gold_per_min":172,
"xp_per_min":167,
"level":8,
"hero_damage":3936,
"tower_damage":0,
"hero_healing":0,
"gold":803,
"gold_spent":2950,
"scaled_hero_damage":3555,
"scaled_tower_damage":0,
"scaled_hero_healing":0,
"ability_upgrades":[
{
"ability":5581,
"time":339,
"level":1
},
{
"ability":5582,
"time":490,
"level":2
},
{
"ability":5581,
"time":580,
"level":3
},
{
"ability":5583,
"time":666,
"level":4
},
{
"ability":5581,
"time":972,
"level":5
},
{
"ability":5584,
"time":1191,
"level":6
},
{
"ability":5581,
"time":1376,
"level":7
},
{
"ability":5583,
"time":1648,
"level":8
}
]

},
{
"account_id":4294967295,
"player_slot":130,
"hero_id":9,
"item_0":29,
"item_1":212,
"item_2":60,
"item_3":41,
"item_4":46,
"item_5":21,
"kills":3,
"deaths":4,
"assists":2,
"leaver_status":0,
"last_hits":53,
"denies":2,
"gold_per_min":267,
"xp_per_min":271,
"level":10,
"hero_damage":3247,
"tower_damage":0,
"hero_healing":0,
"gold":1214,
"gold_spent":4620,
"scaled_hero_damage":3264,
"scaled_tower_damage":0,
"scaled_hero_healing":0,
"ability_upgrades":[
{
"ability":5048,
"time":379,
"level":1
},
{
"ability":5051,
"time":437,
"level":2
},
{
"ability":5051,
"time":472,
"level":3
},
{
"ability":5050,
"time":532,
"level":4
},
{
"ability":5051,
"time":613,
"level":5
},
{
"ability":5049,
"time":710,
"level":6
},
{
"ability":5051,
"time":782,
"level":7
},
{
"ability":5050,
"time":889,
"level":8
},
{
"ability":5048,
"time":1028,
"level":9
},
{
"ability":5048,
"time":1282,
"level":10
}
]

},
{
"account_id":154172491,
"player_slot":131,
"hero_id":104,
"item_0":46,
"item_1":0,
"item_2":37,
"item_3":0,
"item_4":0,
"item_5":215,
"kills":0,
"deaths":6,
"assists":3,
"leaver_status":0,
"last_hits":69,
"denies":20,
"gold_per_min":266,
"xp_per_min":235,
"level":9,
"hero_damage":3456,
"tower_damage":0,
"hero_healing":0,
"gold":910,
"gold_spent":5790,
"scaled_hero_damage":2906,
"scaled_tower_damage":0,
"scaled_hero_healing":0,
"ability_upgrades":[
{
"ability":5597,
"time":400,
"level":1
},
{
"ability":5595,
"time":449,
"level":2
},
{
"ability":5597,
"time":532,
"level":3
},
{
"ability":5596,
"time":610,
"level":4
},
{
"ability":5597,
"time":753,
"level":5
},
{
"ability":5598,
"time":856,
"level":6
},
{
"ability":5595,
"time":1033,
"level":7
},
{
"ability":5597,
"time":1167,
"level":8
},
{
"ability":5595,
"time":1401,
"level":9
}
]

},
{
"account_id":196396031,
"player_slot":132,
"hero_id":80,
"item_0":81,
"item_1":0,
"item_2":29,
"item_3":0,
"item_4":0,
"item_5":0,
"kills":1,
"deaths":3,
"assists":3,
"leaver_status":0,
"last_hits":56,
"denies":1,
"gold_per_min":223,
"xp_per_min":211,
"level":9,
"hero_damage":2656,
"tower_damage":0,
"hero_healing":17,
"gold":840,
"gold_spent":4200,
"scaled_hero_damage":2724,
"scaled_tower_damage":0,
"scaled_hero_healing":6,
"ability_upgrades":[
{
"ability":5412,
"time":294,
"level":1
},
{
"ability":5414,
"time":489,
"level":2
},
{
"ability":5412,
"time":513,
"level":3
},
{
"ability":5413,
"time":630,
"level":4
},
{
"ability":5414,
"time":778,
"level":5
},
{
"ability":5412,
"time":912,
"level":6
},
{
"ability":5415,
"time":1018,
"level":7
},
{
"ability":5412,
"time":1185,
"level":8
},
{
"ability":5413,
"time":1648,
"level":9
}
]
,
"additional_units":[
{
"unitname":"spirit_bear",
"item_0":182,
"item_1":239,
"item_2":29,
"item_3":0,
"item_4":0,
"item_5":0
}
]

}
]
,
"radiant_win":true,
"duration":1296,
"pre_game_duration":90,
"start_time":1479723951,
"match_id":2793488454,
"match_seq_num":2437559609,
"tower_status_radiant":2047,
"tower_status_dire":0,
"barracks_status_radiant":63,
"barracks_status_dire":0,
"cluster":223,
"first_blood_time":39,
"lobby_type":7,
"human_players":10,
"leagueid":0,
"positive_votes":0,
"negative_votes":0,
"game_mode":3,
"flags":1,
"engine":1,
"radiant_score":22,
"dire_score":8
}
}