{
"result":{
"players":[
{
"account_id":136522391,
"player_slot":0,
"hero_id":93,
"item_0":40,
"item_1":125,
"item_2":11,
"item_3":63,
"item_4":46,
"item_5":170,
"kills":1,
"deaths":9,
"assists":2,
"leaver_status":0,
"last_hits":93,
"denies":0,
"gold_per_min":328,
"xp_per_min":362,
"level":13,
"hero_damage":5301,
"tower_damage":121,
"hero_healing":0,
"gold":500,
"gold_spent":9440,
"scaled_hero_damage":3446,
"scaled_tower_damage":64,
"scaled_hero_healing":0,
"ability_upgrades":[
{
"ability":5083,
"time":500,
"level":1
},
{
"ability":5494,
"time":578,
"level":2
},
{
"ability":5083,
"time":665,
"level":3
},
{
"ability":5496,
"time":693,
"level":4
},
{
"ability":5083,
"time":792,
"level":5
},
{
"ability":5369,
"time":866,
"level":6
},
{
"ability":5494,
"time":945,
"level":7
},
{
"ability":5083,
"time":1080,
"level":8
},
{
"ability":5494,
"time":1295,
"level":9
},
{
"ability":5494,
"time":1485,
"level":10
},
{
"ability":5369,
"time":1536,
"level":11
},
{
"ability":5496,
"time":1611,
"level":12
},
{
"ability":5496,
"time":1938,
"level":13
}
]

},
{
"account_id":174450102,
"player_slot":1,
"hero_id":4,
"item_0":104,
"item_1":178,
"item_2":29,
"item_3":244,
"item_4":0,
"item_5":0,
"kills":3,
"deaths":6,
"assists":4,
"leaver_status":0,
"last_hits":17,
"denies":5,
"gold_per_min":306,
"xp_per_min":386,
"level":13,
"hero_damage":23031,
"tower_damage":23,
"hero_healing":0,
"gold":2736,
"gold_spent":4455,
"scaled_hero_damage":12215,
"scaled_tower_damage":21,
"scaled_hero_healing":0,
"ability_upgrades":[
{
"ability":5017,
"time":498,
"level":1
},
{
"ability":5151,
"time":594,
"level":2
},
{
"ability":5017,
"time":679,
"level":3
},
{
"ability":5151,
"time":751,
"level":4
},
{
"ability":5017,
"time":857,
"level":5
},
{
"ability":5151,
"time":948,
"level":6
},
{
"ability":5151,
"time":1005,
"level":7
},
{
"ability":5153,
"time":1415,
"level":8
},
{
"ability":5152,
"time":1597,
"level":9
},
{
"ability":5153,
"time":1935,
"level":10
},
{
"ability":5152,
"time":1935,
"level":11
}
]

},
{
"account_id":174015276,
"player_slot":2,
"hero_id":17,
"item_0":63,
"item_1":0,
"item_2":98,
"item_3":0,
"item_4":239,
"item_5":0,
"kills":2,
"deaths":9,
"assists":1,
"leaver_status":0,
"last_hits":73,
"denies":2,
"gold_per_min":332,
"xp_per_min":289,
"level":11,
"hero_damage":5371,
"tower_damage":77,
"hero_healing":1376,
"gold":889,
"gold_spent":6240,
"scaled_hero_damage":4010,
"scaled_tower_damage":53,
"scaled_hero_healing":603,
"ability_upgrades":[
{
"ability":5368,
"time":446,
"level":1
},
{
"ability":5015,
"time":605,
"level":2
},
{
"ability":5368,
"time":656,
"level":3
},
{
"ability":5015,
"time":780,
"level":4
},
{
"ability":5368,
"time":886,
"level":5
},
{
"ability":5270,
"time":1034,
"level":6
},
{
"ability":5368,
"time":1136,
"level":7
},
{
"ability":5015,
"time":1175,
"level":8
},
{
"ability":5322,
"time":1257,
"level":9
},
{
"ability":5015,
"time":1355,
"level":10
},
{
"ability":5270,
"time":1805,
"level":11
}
]

},
{
"account_id":4294967295,
"player_slot":3,
"hero_id":16,
"item_0":232,
"item_1":29,
"item_2":216,
"item_3":216,
"item_4":216,
"item_5":216,
"kills":0,
"deaths":7,
"assists":6,
"leaver_status":0,
"last_hits":91,
"denies":1,
"gold_per_min":323,
"xp_per_min":345,
"level":12,
"hero_damage":7155,
"tower_damage":0,
"hero_healing":0,
"gold":3696,
"gold_spent":3675,
"scaled_hero_damage":4224,
"scaled_tower_damage":0,
"scaled_hero_healing":0,
"ability_upgrades":[
{
"ability":5103,
"time":427,
"level":1
},
{
"ability":5107,
"time":629,
"level":2
},
{
"ability":5103,
"time":748,
"level":3
},
{
"ability":5107,
"time":946,
"level":4
},
{
"ability":5103,
"time":1175,
"level":5
},
{
"ability":5085,
"time":1287,
"level":6
},
{
"ability":5103,
"time":1441,
"level":7
},
{
"ability":5107,
"time":1485,
"level":8
},
{
"ability":5107,
"time":1630,
"level":9
},
{
"ability":5281,
"time":1817,
"level":10
}
]

},
{
"account_id":89177677,
"player_slot":4,
"hero_id":61,
"item_0":152,
"item_1":40,
"item_2":65,
"item_3":182,
"item_4":170,
"item_5":63,
"kills":0,
"deaths":7,
"assists":1,
"leaver_status":0,
"last_hits":184,
"denies":2,
"gold_per_min":395,
"xp_per_min":491,
"level":15,
"hero_damage":4471,
"tower_damage":0,
"hero_healing":25,
"gold":381,
"gold_spent":9015,
"scaled_hero_damage":3145,
"scaled_tower_damage":0,
"scaled_hero_healing":15,
"ability_upgrades":[
{
"ability":5087,
"time":437,
"level":1
},
{
"ability":5100,
"time":597,
"level":2
},
{
"ability":5100,
"time":613,
"level":3
},
{
"ability":5084,
"time":686,
"level":4
},
{
"ability":5100,
"time":748,
"level":5
},
{
"ability":5018,
"time":885,
"level":6
},
{
"ability":5100,
"time":898,
"level":7
},
{
"ability":5084,
"time":1019,
"level":8
},
{
"ability":5084,
"time":1073,
"level":9
},
{
"ability":5084,
"time":1200,
"level":10
},
{
"ability":5018,
"time":1300,
"level":11
},
{
"ability":5087,
"time":1487,
"level":12
},
{
"ability":5087,
"time":1534,
"level":13
},
{
"ability":5087,
"time":1677,
"level":14
},
{
"ability":5002,
"time":1773,
"level":15
}
]

},
{
"account_id":174818161,
"player_slot":128,
"hero_id":42,
"item_0":247,
"item_1":26,
"item_2":65,
"item_3":63,
"item_4":154,
"item_5":108,
"kills":9,
"deaths":1,
"assists":7,
"leaver_status":0,
"last_hits":204,
"denies":5,
"gold_per_min":867,
"xp_per_min":796,
"level":19,
"hero_damage":13172,
"tower_damage":9943,
"hero_healing":0,
"gold":990,
"gold_spent":21585,
"scaled_hero_damage":11622,
"scaled_tower_damage":7520,
"scaled_hero_healing":0,
"ability_upgrades":[
{
"ability":5267,
"time":535,
"level":1
},
{
"ability":5495,
"time":579,
"level":2
},
{
"ability":5088,
"time":659,
"level":3
},
{
"ability":5267,
"time":680,
"level":4
},
{
"ability":5267,
"time":742,
"level":5
},
{
"ability":5109,
"time":816,
"level":6
},
{
"ability":5495,
"time":877,
"level":7
},
{
"ability":5495,
"time":929,
"level":8
},
{
"ability":5267,
"time":995,
"level":9
},
{
"ability":5495,
"time":1112,
"level":10
},
{
"ability":5109,
"time":1153,
"level":11
},
{
"ability":5088,
"time":1400,
"level":12
},
{
"ability":5088,
"time":1416,
"level":13
},
{
"ability":5088,
"time":1536,
"level":14
},
{
"ability":5002,
"time":1611,
"level":15
},
{
"ability":5109,
"time":1676,
"level":16
},
{
"ability":5002,
"time":1839,
"level":17
},
{
"ability":5002,
"time":1893,
"level":18
},
{
"ability":5002,
"time":1950,
"level":19
}
]

},
{
"account_id":129979651,
"player_slot":129,
"hero_id":73,
"item_0":11,
"item_1":180,
"item_2":182,
"item_3":65,
"item_4":46,
"item_5":204,
"kills":13,
"deaths":1,
"assists":10,
"leaver_status":0,
"last_hits":119,
"denies":5,
"gold_per_min":708,
"xp_per_min":605,
"level":16,
"hero_damage":15065,
"tower_damage":4632,
"hero_healing":0,
"gold":2426,
"gold_spent":15995,
"scaled_hero_damage":13352,
"scaled_tower_damage":2679,
"scaled_hero_healing":0,
"ability_upgrades":[
{
"ability":5280,
"time":431,
"level":1
},
{
"ability":5279,
"time":587,
"level":2
},
{
"ability":5279,
"time":650,
"level":3
},
{
"ability":5280,
"time":729,
"level":4
},
{
"ability":5279,
"time":821,
"level":5
},
{
"ability":5089,
"time":930,
"level":6
},
{
"ability":5279,
"time":991,
"level":7
},
{
"ability":5280,
"time":1142,
"level":8
},
{
"ability":5150,
"time":1170,
"level":9
},
{
"ability":5150,
"time":1281,
"level":10
},
{
"ability":5089,
"time":1382,
"level":11
},
{
"ability":5150,
"time":1573,
"level":12
},
{
"ability":5150,
"time":1595,
"level":13
},
{
"ability":5280,
"time":1702,
"level":14
},
{
"ability":5002,
"time":1817,
"level":15
},
{
"ability":5089,
"time":1877,
"level":16
}
]

},
{
"account_id":155995006,
"player_slot":130,
"hero_id":65,
"item_0":108,
"item_1":36,
"item_2":88,
"item_3":180,
"item_4":129,
"item_5":46,
"kills":6,
"deaths":1,
"assists":20,
"leaver_status":0,
"last_hits":43,
"denies":0,
"gold_per_min":481,
"xp_per_min":455,
"level":14,
"hero_damage":12461,
"tower_damage":939,
"hero_healing":0,
"gold":2331,
"gold_spent":10240,
"scaled_hero_damage":10146,
"scaled_tower_damage":668,
"scaled_hero_healing":0,
"ability_upgrades":[
{
"ability":5102,
"time":419,
"level":1
},
{
"ability":5016,
"time":588,
"level":2
},
{
"ability":5102,
"time":660,
"level":3
},
{
"ability":5016,
"time":760,
"level":4
},
{
"ability":5102,
"time":823,
"level":5
},
{
"ability":5497,
"time":930,
"level":6
},
{
"ability":5102,
"time":1003,
"level":7
},
{
"ability":5016,
"time":1031,
"level":8
},
{
"ability":5016,
"time":1234,
"level":9
},
{
"ability":5099,
"time":1301,
"level":10
},
{
"ability":5497,
"time":1411,
"level":11
},
{
"ability":5099,
"time":1711,
"level":12
},
{
"ability":5099,
"time":1773,
"level":13
},
{
"ability":5099,
"time":1919,
"level":14
}
]

},
{
"account_id":178372095,
"player_slot":131,
"hero_id":19,
"item_0":1,
"item_1":239,
"item_2":214,
"item_3":232,
"item_4":46,
"item_5":102,
"kills":1,
"deaths":3,
"assists":9,
"leaver_status":0,
"last_hits":69,
"denies":1,
"gold_per_min":409,
"xp_per_min":350,
"level":12,
"hero_damage":3436,
"tower_damage":171,
"hero_healing":0,
"gold":1868,
"gold_spent":8700,
"scaled_hero_damage":3122,
"scaled_tower_damage":126,
"scaled_hero_healing":0,
"ability_upgrades":[
{
"ability":5104,
"time":508,
"level":1
},
{
"ability":5086,
"time":577,
"level":2
},
{
"ability":5104,
"time":716,
"level":3
},
{
"ability":5366,
"time":909,
"level":4
},
{
"ability":5104,
"time":1047,
"level":5
},
{
"ability":5323,
"time":1146,
"level":6
},
{
"ability":5104,
"time":1251,
"level":7
},
{
"ability":5366,
"time":1334,
"level":8
},
{
"ability":5366,
"time":1460,
"level":9
},
{
"ability":5366,
"time":1536,
"level":10
},
{
"ability":5323,
"time":1691,
"level":11
},
{
"ability":5086,
"time":1945,
"level":12
}
]

},
{
"account_id":314872184,
"player_slot":132,
"hero_id":34,
"item_0":129,
"item_1":121,
"item_2":41,
"item_3":201,
"item_4":46,
"item_5":29,
"kills":8,
"deaths":2,
"assists":15,
"leaver_status":0,
"last_hits":73,
"denies":0,
"gold_per_min":564,
"xp_per_min":561,
"level":16,
"hero_damage":11160,
"tower_damage":1082,
"hero_healing":1291,
"gold":942,
"gold_spent":13430,
"scaled_hero_damage":10798,
"scaled_tower_damage":719,
"scaled_hero_healing":420,
"ability_upgrades":[
{
"ability":5320,
"time":422,
"level":1
},
{
"ability":5106,
"time":555,
"level":2
},
{
"ability":5106,
"time":641,
"level":3
},
{
"ability":5320,
"time":667,
"level":4
},
{
"ability":5106,
"time":758,
"level":5
},
{
"ability":5320,
"time":813,
"level":6
},
{
"ability":5101,
"time":895,
"level":7
},
{
"ability":5320,
"time":1003,
"level":8
},
{
"ability":5106,
"time":1137,
"level":9
},
{
"ability":5098,
"time":1227,
"level":10
},
{
"ability":5101,
"time":1296,
"level":11
},
{
"ability":5098,
"time":1581,
"level":12
},
{
"ability":5098,
"time":1612,
"level":13
},
{
"ability":5098,
"time":1722,
"level":14
},
{
"ability":5002,
"time":1841,
"level":15
},
{
"ability":5002,
"time":1968,
"level":16
}
]

}
]
,
"radiant_win":false,
"duration":1505,
"pre_game_duration":90,
"start_time":1480855605,
"match_id":2822669761,
"match_seq_num":2462998758,
"tower_status_radiant":0,
"tower_status_dire":2047,
"barracks_status_radiant":0,
"barracks_status_dire":63,
"cluster":227,
"first_blood_time":131,
"lobby_type":0,
"human_players":10,
"leagueid":0,
"positive_votes":0,
"negative_votes":0,
"game_mode":18,
"flags":1,
"engine":1,
"radiant_score":8,
"dire_score":37
}
}